mongogeneric/__init__.py
mongogeneric/detail.py
mongogeneric/edit.py
mongogeneric/list.py
mongogeneric3-0.0.2.dist-info/DESCRIPTION.rst
mongogeneric3-0.0.2.dist-info/METADATA
mongogeneric3-0.0.2.dist-info/RECORD
mongogeneric3-0.0.2.dist-info/WHEEL
mongogeneric3-0.0.2.dist-info/metadata.json
mongogeneric3-0.0.2.dist-info/top_level.txt
