Metadata-Version: 2.0
Name: mongogeneric3
Version: 0.0.2
Summary: An implementation of django class based generic views using mongoengine.
Home-page: http://github.com/lgaticaq/django-mongogeneric
Author: Leonardo Gatica
Author-email: lgatica@protonmail.com
License: MIT
Keywords: mongo cbv mongoengine
Platform: UNKNOWN
Classifier: Development Status :: 5 - Production/Stable
Classifier: Intended Audience :: Developers
Classifier: Natural Language :: English
Classifier: License :: OSI Approved :: MIT License
Classifier: Operating System :: OS Independent
Classifier: Programming Language :: Python :: 2.7
Classifier: Programming Language :: Python :: 3.5
Classifier: Topic :: Software Development :: Libraries :: Python Modules
